nedo_vision_worker_core/__init__.py
nedo_vision_worker_core/cli.py
nedo_vision_worker_core/core_service.py
nedo_vision_worker_core/doctor.py
nedo_vision_worker_core/ai/FrameDrawer.py
nedo_vision_worker_core/ai/ImageDebugger.py
nedo_vision_worker_core/ai/VideoDebugger.py
nedo_vision_worker_core/ai/__init__.py
nedo_vision_worker_core/callbacks/DetectionCallbackManager.py
nedo_vision_worker_core/callbacks/DetectionCallbackTypes.py
nedo_vision_worker_core/callbacks/__init__.py
nedo_vision_worker_core/config/ConfigurationManager.py
nedo_vision_worker_core/config/__init__.py
nedo_vision_worker_core/database/DatabaseManager.py
nedo_vision_worker_core/database/__init__.py
nedo_vision_worker_core/detection/BaseDetector.py
nedo_vision_worker_core/detection/RFDETRDetector.py
nedo_vision_worker_core/detection/YOLODetector.py
nedo_vision_worker_core/detection/__init__.py
nedo_vision_worker_core/detection/detection_processing/DetectionProcessor.py
nedo_vision_worker_core/detection/detection_processing/HumanDetectionProcessor.py
nedo_vision_worker_core/detection/detection_processing/PPEDetectionProcessor.py
nedo_vision_worker_core/detection/detection_processing/__init__.py
nedo_vision_worker_core/drawing_assets/blue/inner_corner.png
nedo_vision_worker_core/drawing_assets/blue/inner_frame.png
nedo_vision_worker_core/drawing_assets/blue/line.png
nedo_vision_worker_core/drawing_assets/blue/top_left.png
nedo_vision_worker_core/drawing_assets/blue/top_right.png
nedo_vision_worker_core/drawing_assets/red/inner_corner.png
nedo_vision_worker_core/drawing_assets/red/inner_frame.png
nedo_vision_worker_core/drawing_assets/red/line.png
nedo_vision_worker_core/drawing_assets/red/top_left.png
nedo_vision_worker_core/drawing_assets/red/top_right.png
nedo_vision_worker_core/icons/boots-green.png
nedo_vision_worker_core/icons/boots-red.png
nedo_vision_worker_core/icons/gloves-green.png
nedo_vision_worker_core/icons/gloves-red.png
nedo_vision_worker_core/icons/goggles-green.png
nedo_vision_worker_core-0.4.10.dist-info/METADATA
nedo_vision_worker_core-0.4.10.dist-info/WHEEL
nedo_vision_worker_core-0.4.10.dist-info/entry_points.txt
nedo_vision_worker_core-0.4.10.dist-info/top_level.txt
nedo_vision_worker_core-0.4.10.dist-info/RECORD
