Metadata-Version: 2.4
Name: nedo-vision-worker-core
Version: 0.4.10
Summary: Nedo Vision Worker Core Library for AI Vision Processing
Author-email: Willy Achmat Fauzi <willy.achmat@gmail.com>
Maintainer-email: Willy Achmat Fauzi <willy.achmat@gmail.com>
License-Expression: MIT
Project-URL: Homepage, https://gitlab.com/sindika/research/nedo-vision/nedo-vision-worker-core-v2
Project-URL: Documentation, https://gitlab.com/sindika/research/nedo-vision/nedo-vision-worker-core-v2/-/blob/main/README.md
Project-URL: Repository, https://gitlab.com/sindika/research/nedo-vision/nedo-vision-worker-core-v2
Project-URL: Bug Reports, https://gitlab.com/sindika/research/nedo-vision/nedo-vision-worker-core-v2/-/issues
Keywords: computer-vision,machine-learning,ai,worker-core,deep-learning,object-detection,neural-networks,video-processing,pytorch,yolo
Classifier: Development Status :: 4 - Beta
Classifier: Intended Audience :: Developers
Classifier: Operating System :: OS Independent
Classifier: Programming Language :: Python :: 3
Classifier: Programming Language :: Python :: 3 :: Only
Classifier: Programming Language :: Python :: 3.8
Classifier: Programming Language :: Python :: 3.9
Classifier: Programming Language :: Python :: 3.10
Classifier: Programming Language :: Python :: 3.11
Classifier: Programming Language :: Python :: 3.12
Classifier: Programming Language :: Python :: 3.13
Classifier: Topic :: Software Development :: Libraries :: Python Modules
Classifier: Topic :: Multimedia :: Video
Classifier: Topic :: Scientific/Engineering :: Artificial Intelligence
Classifier: Topic :: System :: Hardware
Classifier: Environment :: GPU
Classifier: Environment :: No Input/Output (Daemon)
Requires-Python: >=3.8
Requires-Dist: alembic>=1.8.0
Requires-Dist: numpy<2.0.0,>=1.21.0
Requires-Dist: pillow>=8.0.0
Requires-Dist: psutil>=5.9.0
Requires-Dist: scipy>=1.9.0
Requires-Dist: shapely>=1.8.0
Requires-Dist: SQLAlchemy>=1.4.0
Requires-Dist: torch>=1.9.0
Requires-Dist: torchvision>=0.10.0
Requires-Dist: ultralytics>=8.0.0
Requires-Dist: rfdetr<2.0.0,>=1.2.0
Provides-Extra: dev
Requires-Dist: pytest>=7.0.0; extra == "dev"
Requires-Dist: black>=22.0.0; extra == "dev"
Requires-Dist: isort>=5.10.0; extra == "dev"
Requires-Dist: mypy>=0.950; extra == "dev"
Requires-Dist: flake8>=4.0.0; extra == "dev"
Requires-Dist: pre-commit>=2.17.0; extra == "dev"
Provides-Extra: opencv
Requires-Dist: opencv-python<5.0.0,>=4.6.0; extra == "opencv"
